README.rst
pyproject.toml
setup.py
oaai/__init__.py
oaai/__main__.py
oaai/cache.py
oaai/client.py
oaai/disk.py
oaai/error.py
oaai/event.py
oaai/find.py
oaai/fleet.py
oaai/object.py
oaai/reactor.py
oaai/thread.py
oaai/timer.py
oaai/utils.py
oaai/workdir.py
oaai.egg-info/PKG-INFO
oaai.egg-info/SOURCES.txt
oaai.egg-info/dependency_links.txt
oaai.egg-info/entry_points.txt
oaai.egg-info/top_level.txt
oaai/modules/__init__.py
oaai/modules/dbg.py
oaai/modules/err.py
oaai/modules/flt.py
oaai/modules/fnd.py
oaai/modules/irc.py
oaai/modules/llm.py
oaai/modules/log.py
oaai/modules/man.py
oaai/modules/mbx.py
oaai/modules/mod.py
oaai/modules/rss.py
oaai/modules/rst.py
oaai/modules/tbl.py
oaai/modules/tdo.py
oaai/modules/thr.py
oaai/modules/tmr.py
oaai/modules/udp.py
oaai/modules/upt.py