Metadata-Version: 2.1
Name: oaai
Version: 2
Summary: Open Authoritative Artificial Intelligence (OAAI)
Author-email: Bart Thate <bthate@dds.nl>
License: Public Domain
Project-URL: home, https://pypi.org/project/oaai
Project-URL: bugs, https://github.com/bthate/oaai/issues
Project-URL: source, https://github.com/bthate/oaai
Classifier: Development Status :: 3 - Alpha
Classifier: License :: Public Domain
Classifier: Operating System :: Unix
Classifier: Programming Language :: Python :: 3
Classifier: Topic :: Utilities
